decimal_to_hex2/__init__.py
decimal_to_hex2/check.py
decimal_to_hex2/mycode.py
decimal_to_hex2-0.0.1.dist-info/LICENSE
decimal_to_hex2-0.0.1.dist-info/METADATA
decimal_to_hex2-0.0.1.dist-info/WHEEL
decimal_to_hex2-0.0.1.dist-info/top_level.txt
decimal_to_hex2-0.0.1.dist-info/RECORD
